{
    "version": "0.2",
    "ignorePaths": [],
    "dictionaryDefinitions": [],
    "dictionaries": [],
    "words": [
        "Activatible",
        "aggs",
        "agregad",
        "apos",
        "appender",
        "appenders",
        "assrt",
        "bgcolor",
        "bson",
        "cacheable",
        "Cacher",
        "Catchable",
        "classname",
        "codegen",
        "contenttype",
        "cpus",
        "creds",
        "cullable",
        "darkgrey",
        "DATETIME",
        "dbconfig",
        "deserialize",
        "expirable",
        "extends",
        "fastify",
        "Firestore",
        "formbody",
        "globbing",
        "graphicsmagick",
        "gulpfile",
        "hardbreak",
        "hasher",
        "hyphenator",
        "idle",
        "ilike",
        "import",
        "Indicies",
        "injectable",
        "Inno",
        "instanceof",
        "iregex",
        "jameskyburz",
        "jpegoptim",
        "jpegotim",
        "LICENCE",
        "lifecycle",
        "linebreak",
        "LOCALSTACK",
        "masylum's",
        "maxlength",
        "MEDIUMINT",
        "metadata",
        "millis",
        "mkdir",
        "mtlynch",
        "nics",
        "nocase",
        "nodesh",
        "npmignore",
        "ondeck",
        "oneline",
        "openapi",
        "optoken",
        "pageable",
        "parens",
        "patt",
        "pgcrypto",
        "picomatch",
        "pngquant",
        "prismjs",
        "promisify",
        "proxied",
        "proxying",
        "readonly",
        "recurse",
        "regexes",
        "Reindex",
        "Renderable",
        "repo",
        "Retargetting",
        "SAVEPOINT",
        "serverless",
        "shomatan",
        "SIGINT",
        "SIGKILL",
        "SIGTERM",
        "singleline",
        "softbreak",
        "speciality",
        "string",
        "sublayout",
        "subsetting",
        "subsubtitle",
        "templating",
        "testcase",
        "testsuite",
        "testsuites",
        "timeout",
        "TINYINT",
        "todo",
        "Todos",
        "Transpiled",
        "transpiler",
        "transpiling",
        "travetto",
        "trunc",
        "tslib",
        "typeof",
        "uction",
        "unwatching",
        "upsert",
        "upserted",
        "upserts",
        "validators",
        "valign",
        "vendia",
        "Waitable",
        "woah",
        "WORKDIR",
        "Writeonly",
        "xcopy",
        "xpack",
        "XPOST",
        "Xunit",
        "@trv",
        "Ⲑfile",
        "Ⲑlog",
        "Ⲑmeta",
        "Ⲑinit",
        "ᚕtrv"
    ],
    "ignoreWords": [],
    "import": []
}